aliyunsdksophonsoar/__init__.py
aliyunsdksophonsoar/request/__init__.py
aliyunsdksophonsoar/request/v20220728/ComparePlaybooksRequest.py
aliyunsdksophonsoar/request/v20220728/ConvertPlaybookRequest.py
aliyunsdksophonsoar/request/v20220728/CopyPlaybookRequest.py
aliyunsdksophonsoar/request/v20220728/CreatePlaybookRequest.py
aliyunsdksophonsoar/request/v20220728/DebugPlaybookRequest.py
aliyunsdksophonsoar/request/v20220728/DeleteComponentAssetRequest.py
aliyunsdksophonsoar/request/v20220728/DeletePlaybookRequest.py
aliyunsdksophonsoar/request/v20220728/DescribeComponentAssetFormRequest.py
aliyunsdksophonsoar/request/v20220728/DescribeComponentAssetsRequest.py
aliyunsdksophonsoar/request/v20220728/DescribeComponentListRequest.py
aliyunsdksophonsoar/request/v20220728/DescribeComponentPlaybookRequest.py
aliyunsdksophonsoar/request/v20220728/DescribeComponentsJsRequest.py
aliyunsdksophonsoar/request/v20220728/DescribeDistinctReleasesRequest.py
aliyunsdksophonsoar/request/v20220728/DescribeEnumItemsRequest.py
aliyunsdksophonsoar/request/v20220728/DescribeExecutePlaybooksRequest.py
aliyunsdksophonsoar/request/v20220728/DescribeFieldRequest.py
aliyunsdksophonsoar/request/v20220728/DescribeGroupProductionsRequest.py
aliyunsdksophonsoar/request/v20220728/DescribeLatestRecordSchemaRequest.py
aliyunsdksophonsoar/request/v20220728/DescribeNodeParamTagsRequest.py
aliyunsdksophonsoar/request/v20220728/DescribeNotifyTemplateListRequest.py
aliyunsdksophonsoar/request/v20220728/DescribeOpenApiInfoRequest.py
aliyunsdksophonsoar/request/v20220728/DescribeOpenApiListRequest.py
aliyunsdksophonsoar/request/v20220728/DescribePlaybookInputOutputRequest.py
aliyunsdksophonsoar/request/v20220728/DescribePlaybookMetricsRequest.py
aliyunsdksophonsoar/request/v20220728/DescribePlaybookNodesOutputRequest.py
aliyunsdksophonsoar/request/v20220728/DescribePlaybookNumberMetricsRequest.py
aliyunsdksophonsoar/request/v20220728/DescribePlaybookReleasesRequest.py
aliyun_python_sdk_sophonsoar-1.0.1.dist-info/LICENSE
aliyun_python_sdk_sophonsoar-1.0.1.dist-info/METADATA
aliyun_python_sdk_sophonsoar-1.0.1.dist-info/WHEEL
aliyun_python_sdk_sophonsoar-1.0.1.dist-info/top_level.txt
aliyun_python_sdk_sophonsoar-1.0.1.dist-info/RECORD
